functions_by_krystsinali/README.md
functions_by_krystsinali/math_functions.py
functions_by_krystsinali-0.4.0.dist-info/WHEEL
functions_by_krystsinali-0.4.0.dist-info/METADATA
functions_by_krystsinali-0.4.0.dist-info/RECORD
