Metadata-Version: 2.1
Name: functions-by-krystsinali
Version: 0.4.0
Summary: This is our test project
Author: Krystsina Liaudanskaya
Author-email: krystsinali@gmail.com
Requires-Python: >=3.10,<4.0
Classifier: Programming Language :: Python :: 3
Classifier: Programming Language :: Python :: 3.10
Classifier: Programming Language :: Python :: 3.11
